aselenium/__init__.py
aselenium/actions.py
aselenium/alert.py
aselenium/command.py
aselenium/connection.py
aselenium/element.py
aselenium/errors.py
aselenium/logs.py
aselenium/options.py
aselenium/service.py
aselenium/session.py
aselenium/settings.py
aselenium/shadow.py
aselenium/utils.py
aselenium/valuewrap.py
aselenium/webdriver.py
aselenium/chrome/__init__.py
aselenium/chrome/options.py
aselenium/chrome/service.py
aselenium/chrome/session.py
aselenium/chrome/webdriver.py
aselenium/chromium/__init__.py
aselenium/chromium/options.py
aselenium/chromium/service.py
aselenium/chromium/session.py
aselenium/chromium/webdriver.py
aselenium/edge/__init__.py
aselenium/edge/options.py
aselenium/edge/service.py
aselenium/edge/session.py
aselenium/edge/webdriver.py
aselenium/firefox/__init__.py
aselenium/firefox/options.py
aselenium/firefox/service.py
aselenium/firefox/session.py
aselenium/firefox/utils.py
aselenium/firefox/webdriver.py
aselenium/javascript/__init__.py
aselenium/javascript/get_attribute.py
aselenium/javascript/is_viewable.py
aselenium/manager/__init__.py
aselenium/manager/driver.py
aselenium/manager/file.py
aselenium/manager/version.py
aselenium/safari/__init__.py
aselenium/safari/options.py
aselenium/safari/service.py
aselenium/safari/session.py
aselenium/safari/webdriver.py
aselenium-1.0.5.dist-info/licenses/LICENSE
aselenium-1.0.5.dist-info/METADATA
aselenium-1.0.5.dist-info/WHEEL
aselenium-1.0.5.dist-info/top_level.txt
aselenium-1.0.5.dist-info/RECORD
