Metadata-Version: 2.4
Name: aselenium
Version: 1.0.5
Summary: Asyncronous implementation of web browser automation for Python.
Home-page: https://github.com/AresJef/Aselenium
Author: Jiefu Chen
Author-email: keppa1991@163.com
License: Apache License 2.0
Keywords: async,asyncronous,automation,arsenic,selenium
Classifier: Programming Language :: Python :: 3
Classifier: Operating System :: Unix
Classifier: Operating System :: MacOS :: MacOS X
Classifier: Operating System :: Microsoft :: Windows
Requires-Python: >=3.10
License-File: LICENSE
Requires-Dist: aiohttp>=3.8.4
Requires-Dist: pandas>=2.1.0
Requires-Dist: psutil>=5.8.0
Requires-Dist: pyarrow>=12.0.1
Requires-Dist: orjson>=3.9.5
Dynamic: license-file
